setup.py
pya0-0.3.7.dist-info/METADATA
pya0-0.3.7.dist-info/WHEEL
pya0-0.3.7.dist-info/RECORD
pya0-0.3.7.dist-info/top_level.txt
pya0.libs/libz-7fd423a0.so.1.2.8
pya0.libs/liblzma-5b8415cf.so.5.2.2
pya0.libs/libxml2-b0f1a615.so.2.9.4
pya0.libs/libhwloc-811858d2.so.5.7.2
pya0.libs/libopen-rte-6abe1f34.so.20.1.0
pya0.libs/libicuuc-5743fca1.so.57.1
pya0.libs/libopen-pal-321722b9.so.20.2.0
pya0.libs/libmpi-69c5bc42.so.20.0.2
pya0.libs/libicudata-79cf9efa.so.57.1
pya0.libs/libnuma-c8473f23.so.1.0.0
pya0.libs/libicui18n-03536ef3.so.57.1
pya0.libs/libevent-2-6d3aa264.0.so.5.1.9
pya0.libs/libltdl-738907ff.so.7
pya0/mse-aops-2021-train-data.py
pya0/transformer_eval.py
pya0/eval.py
pya0/fusion_analysis.py
pya0/visualize.py
pya0/auto_eval.py
pya0/msearch.py
pya0/arqmath-2021-train-data.py
pya0/crossvalidate.py
pya0/corpus_converter.py
pya0/mse-aops-2021.py
pya0/index_manager.py
pya0/auc_roc.py
pya0/__init__.py
pya0/transformer_utils.py
pya0/_pya0.so
pya0/preprocess.py
pya0/mergerun.py
pya0/judge_rate.py
pya0/l2r.py
pya0/lambdaMART.py
pya0/torch_train.py
pya0/arqmath-2021.py
pya0/timer.py
pya0/effectiveness_ttest.py
pya0/condenser.py
pya0/replace_post_tex.py
pya0/corpus_reader.py
pya0/rm3.py
pya0/transformer.py
pya0/mindex_info.py
pya0/collection_driver.py
pya0/__main__.py
pya0/splade_math_mask.py
pya0/topics-and-qrels/tsv2topics.py
pya0/topics-and-qrels/qrels.arqmath-2021-task2-official.v3.txt
pya0/topics-and-qrels/topics.arqmath-2020-task1-origin.xml
pya0/topics-and-qrels/qrels.arqmath-2021-task2-official.txt
pya0/topics-and-qrels/topics.arqmath-2022-task1-manual.txt
pya0/topics-and-qrels/topics.arqmath-2022-task2-origin.xml
pya0/topics-and-qrels/topics.arqmath-2021-task2-official.txt
pya0/topics-and-qrels/topics.arqmath-2020-task2-origin.xml
pya0/topics-and-qrels/qrels.arqmath-2021-task1.txt
pya0/topics-and-qrels/topics.arqmath-2021-task1.txt
pya0/topics-and-qrels/qrels.arqmath-2021-task1-official.txt
pya0/topics-and-qrels/topics.arqmath-2021-task1-refined.txt
pya0/topics-and-qrels/qrels.arqmath-2021-task2.txt
