Metadata-Version: 2.1
Name: pya0
Version: 0.3.7
Summary: Approach Zero Python Interface
Home-page: UNKNOWN
Author: Wei Zhong
Author-email: clock126@126.com
License: UNKNOWN
Platform: UNKNOWN
Classifier: Programming Language :: Python :: 3
Classifier: License :: OSI Approved :: MIT License
Classifier: Operating System :: OS Independent
Requires-Python: >=3.5
Requires-Dist: tqdm
Requires-Dist: pandas
Requires-Dist: nltk
